type_safe_mq/__init__.py
type_safe_mq/envelope.py
type_safe_mq-0.1.3.dist-info/METADATA
type_safe_mq-0.1.3.dist-info/WHEEL
type_safe_mq-0.1.3.dist-info/top_level.txt
type_safe_mq-0.1.3.dist-info/RECORD
