Metadata-Version: 2.4
Name: type-safe-mq
Version: 0.1.3
Summary: Type-safe Protobuf envelope utility for message queues
Author-email: drkyun <kyunn299@icloud.com>
License: MIT
Project-URL: Homepage, https://github.com/prismtech-dev/type-safe-mq
Project-URL: Source, https://github.com/prismtech-dev/type-safe-mq
Requires-Python: >=3.9
Requires-Dist: protobuf>=4.0.0
